sqla_wrapper/__init__.py
sqla_wrapper/alembic_wrapper.py
sqla_wrapper/base_model.py
sqla_wrapper/paginator.py
sqla_wrapper/session.py
sqla_wrapper/sqlalchemy_wrapper.py
sqla_wrapper/cli/__init__.py
sqla_wrapper/cli/click_cli.py
sqla_wrapper/cli/proper_cli_cli.py
sqla_wrapper-5.6.2.dist-info/METADATA
sqla_wrapper-5.6.2.dist-info/MIT-LICENSE
sqla_wrapper-5.6.2.dist-info/WHEEL
sqla_wrapper-5.6.2.dist-info/top_level.txt
sqla_wrapper-5.6.2.dist-info/RECORD
