Metadata-Version: 2.1
Name: sqla-wrapper
Version: 5.6.2
Summary: A framework-independent modern wrapper for SQLAlchemy & Alembic.
Home-page: https://github.com/jpsca/sqla-wrapper
Author: Juan-Pablo Scaletti
Author-email: juanpablo@jpscaletti.com
License: MIT
Project-URL: Documentation, https://sqla-wrapper.scaletti.dev/
Project-URL: Issue tracker, https://github.com/jpsca/sqla-wrapper/issues
Classifier: Development Status :: 5 - Production/Stable
Classifier: Environment :: Web Environment
Classifier: Intended Audience :: Developers
Classifier: License :: OSI Approved :: MIT License
Classifier: Topic :: Database
Classifier: Programming Language :: Python :: 3.7
Classifier: Programming Language :: Python :: 3.8
Classifier: Programming Language :: Python :: 3.9
Classifier: Programming Language :: Python :: 3.10
Requires-Python: <4.0,>=3.7
License-File: MIT-LICENSE
Requires-Dist: sqlalchemy (>=1.4)
Requires-Dist: alembic (>=1.6)
Provides-Extra: dev
Requires-Dist: flake8 ; extra == 'dev'
Requires-Dist: flake8-bugbear ; extra == 'dev'
Requires-Dist: flake8-logging-format ; extra == 'dev'
Requires-Dist: flake8-quotes ; extra == 'dev'
Requires-Dist: mypy ; extra == 'dev'
Requires-Dist: pre-commit ; extra == 'dev'
Requires-Dist: pytest-cov ; extra == 'dev'
Requires-Dist: sqlalchemy[mypy] ; extra == 'dev'
Requires-Dist: tox ; extra == 'dev'
Provides-Extra: test
Requires-Dist: psycopg2-binary ; extra == 'test'
Requires-Dist: pytest ; extra == 'test'
Requires-Dist: flask ; extra == 'test'
Requires-Dist: click ; extra == 'test'
Requires-Dist: proper-cli (>=1.0) ; extra == 'test'
